ShujuKeshihuaDeJichuzhishi/README.md
ShujuKeshihuaDeJichuzhishi/__init__.py
ShujuKeshihuaDeJichuzhishi/__main__.py
ShujuKeshihuaDeJichuzhishi/file.epub
ShujuKeshihuaDeJichuzhishi/index.html
ShujuKeshihuaDeJichuzhishi/css/__init__.py
ShujuKeshihuaDeJichuzhishi/css/annotations.css
ShujuKeshihuaDeJichuzhishi/css/main.css
ShujuKeshihuaDeJichuzhishi/css/normalize.css
ShujuKeshihuaDeJichuzhishi/css/popup.css
ShujuKeshihuaDeJichuzhishi/font/__init__.py
ShujuKeshihuaDeJichuzhishi/font/fontello.eot
ShujuKeshihuaDeJichuzhishi/font/fontello.svg
ShujuKeshihuaDeJichuzhishi/font/fontello.ttf
ShujuKeshihuaDeJichuzhishi/font/fontello.woff
ShujuKeshihuaDeJichuzhishi/img/__init__.py
ShujuKeshihuaDeJichuzhishi/img/annotator-glyph-sprite.png
ShujuKeshihuaDeJichuzhishi/img/annotator-icon-sprite.png
ShujuKeshihuaDeJichuzhishi/img/apple-touch-icon.png
ShujuKeshihuaDeJichuzhishi/img/cancelfullscreen.png
ShujuKeshihuaDeJichuzhishi/img/close.png
ShujuKeshihuaDeJichuzhishi/img/fullscreen.png
ShujuKeshihuaDeJichuzhishi/img/loader.gif
ShujuKeshihuaDeJichuzhishi/img/menu-icon.png
ShujuKeshihuaDeJichuzhishi/img/save.png
ShujuKeshihuaDeJichuzhishi/img/saved.png
ShujuKeshihuaDeJichuzhishi/img/settings-s.png
ShujuKeshihuaDeJichuzhishi/img/settings.png
ShujuKeshihuaDeJichuzhishi/img/star.png
ShujuKeshihuaDeJichuzhishi/js/__init__.py
ShujuKeshihuaDeJichuzhishi/js/epub.js
ShujuKeshihuaDeJichuzhishi/js/epub.min.js
ShujuKeshihuaDeJichuzhishi/js/epub.min.map
ShujuKeshihuaDeJichuzhishi/js/hooks.min.js
ShujuKeshihuaDeJichuzhishi/js/hooks.min.map
ShujuKeshihuaDeJichuzhishi/js/reader.js
ShujuKeshihuaDeJichuzhishi/js/reader.js.map
ShujuKeshihuaDeJichuzhishi/js/reader.min.js
ShujuKeshihuaDeJichuzhishi/js/reader.min.map
ShujuKeshihuaDeJichuzhishi/js/hooks/__init__.py
ShujuKeshihuaDeJichuzhishi/js/hooks/extensions/__init__.py
ShujuKeshihuaDeJichuzhishi/js/hooks/extensions/highlight.js
ShujuKeshihuaDeJichuzhishi/js/libs/__init__.py
ShujuKeshihuaDeJichuzhishi/js/libs/jquery.min.js
shuju_keshihua_de_jichuzhishi-2024.3.5.0.dist-info/METADATA
shuju_keshihua_de_jichuzhishi-2024.3.5.0.dist-info/WHEEL
shuju_keshihua_de_jichuzhishi-2024.3.5.0.dist-info/entry_points.txt
shuju_keshihua_de_jichuzhishi-2024.3.5.0.dist-info/top_level.txt
shuju_keshihua_de_jichuzhishi-2024.3.5.0.dist-info/RECORD
